main.py
mcp_server.py
iflow_mcp_burpsuite_mcp_server-1.0.0.dist-info/licenses/LICENSE
iflow_mcp_burpsuite_mcp_server-1.0.0.dist-info/METADATA
iflow_mcp_burpsuite_mcp_server-1.0.0.dist-info/WHEEL
iflow_mcp_burpsuite_mcp_server-1.0.0.dist-info/entry_points.txt
iflow_mcp_burpsuite_mcp_server-1.0.0.dist-info/top_level.txt
iflow_mcp_burpsuite_mcp_server-1.0.0.dist-info/RECORD
