Metadata-Version: 2.4
Name: iflow-mcp_burpsuite-mcp-server
Version: 1.0.0
Summary: A powerful Model Context Protocol (MCP) server implementation for BurpSuite, providing programmatic access to Burp's core functionalities.
Author-email: X3r0K <x3r0k@example.com>
License: MIT
Project-URL: Homepage, https://github.com/X3r0K/BurpSuite-MCP-Server
Project-URL: Repository, https://github.com/X3r0K/BurpSuite-MCP-Server
Project-URL: Issues, https://github.com/X3r0K/BurpSuite-MCP-Server/issues
Classifier: Development Status :: 4 - Beta
Classifier: Intended Audience :: Developers
Classifier: License :: OSI Approved :: MIT License
Classifier: Programming Language :: Python :: 3
Classifier: Programming Language :: Python :: 3.8
Classifier: Programming Language :: Python :: 3.9
Classifier: Programming Language :: Python :: 3.10
Classifier: Programming Language :: Python :: 3.11
Classifier: Programming Language :: Python :: 3.12
Requires-Python: >=3.8
License-File: LICENSE
Requires-Dist: fastapi==0.104.1
Requires-Dist: uvicorn==0.24.0
Requires-Dist: python-multipart==0.0.6
Requires-Dist: requests==2.31.0
Requires-Dist: python-jose==3.3.0
Requires-Dist: python-dotenv==1.0.0
Requires-Dist: pydantic==2.4.2
Requires-Dist: aiohttp==3.9.1
Requires-Dist: websockets==12.0
Dynamic: license-file
